{
  "clubId": "aston-villa",
  "era": "2022",
  "label": "2022",
  "players": [
    {
      "id": "202811",
      "name": "Damián Emiliano Martínez",
      "position": "GK",
      "positionGroup": "GK",
      "rating": 84,
      "nationality": "Argentina",
      "photoUrl": "https://cdn.sofifa.net/players/202/811/22_120.png"
    },
    {
      "id": "229906",
      "name": "Leon Bailey Butler",
      "position": "RM",
      "positionGroup": "MID",
      "rating": 82,
      "nationality": "Jamaica",
      "photoUrl": "https://cdn.sofifa.net/players/229/906/22_120.png"
    },
    {
      "id": "195859",
      "name": "Daniel William John Ings",
      "position": "ST",
      "positionGroup": "FWD",
      "rating": 81,
      "nationality": "England",
      "photoUrl": "https://cdn.sofifa.net/players/195/859/22_120.png"
    },
    {
      "id": "226162",
      "name": "Emiliano Buendía",
      "position": "RM",
      "positionGroup": "MID",
      "rating": 79,
      "nationality": "Argentina",
      "photoUrl": "https://cdn.sofifa.net/players/226/162/22_120.png"
    },
    {
      "id": "152908",
      "name": "Ashley Young",
      "position": "LWB",
      "positionGroup": "DEF",
      "rating": 78,
      "nationality": "England",
      "photoUrl": "https://cdn.sofifa.net/players/152/908/22_120.png"
    },
    {
      "id": "210881",
      "name": "John McGinn",
      "position": "CDM",
      "positionGroup": "MID",
      "rating": 78,
      "nationality": "Scotland",
      "photoUrl": "https://cdn.sofifa.net/players/210/881/22_120.png"
    },
    {
      "id": "212419",
      "name": "Tyrone Mings",
      "position": "CB",
      "positionGroup": "DEF",
      "rating": 78,
      "nationality": "England",
      "photoUrl": "https://cdn.sofifa.net/players/212/419/22_120.png"
    },
    {
      "id": "221697",
      "name": "Ollie Watkins",
      "position": "ST",
      "positionGroup": "FWD",
      "rating": 78,
      "nationality": "England",
      "photoUrl": "https://cdn.sofifa.net/players/221/697/22_120.png"
    },
    {
      "id": "227174",
      "name": "Matty Cash",
      "position": "RB",
      "positionGroup": "DEF",
      "rating": 78,
      "nationality": "England",
      "photoUrl": "https://cdn.sofifa.net/players/227/174/22_120.png"
    },
    {
      "id": "227678",
      "name": "Ezri Konsa Ngoyo",
      "position": "CB",
      "positionGroup": "DEF",
      "rating": 78,
      "nationality": "England",
      "photoUrl": "https://cdn.sofifa.net/players/227/678/22_120.png"
    },
    {
      "id": "207948",
      "name": "Bertrand Isidore Traoré",
      "position": "RM",
      "positionGroup": "MID",
      "rating": 77,
      "nationality": "Burkina Faso",
      "photoUrl": "https://cdn.sofifa.net/players/207/948/22_120.png"
    },
    {
      "id": "218659",
      "name": "Matt Targett",
      "position": "LB",
      "positionGroup": "DEF",
      "rating": 77,
      "nationality": "England",
      "photoUrl": "https://cdn.sofifa.net/players/218/659/22_120.png"
    },
    {
      "id": "236499",
      "name": "Douglas Luiz Soares de Paulo",
      "position": "CDM",
      "positionGroup": "MID",
      "rating": 77,
      "nationality": "Brazil",
      "photoUrl": "https://cdn.sofifa.net/players/236/499/22_120.png"
    },
    {
      "id": "210896",
      "name": "Morgan Sanson",
      "position": "CM",
      "positionGroup": "MID",
      "rating": 76,
      "nationality": "France",
      "photoUrl": "https://cdn.sofifa.net/players/210/896/22_120.png"
    },
    {
      "id": "216433",
      "name": "Anwar El Ghazi",
      "position": "LM",
      "positionGroup": "MID",
      "rating": 76,
      "nationality": "Netherlands",
      "photoUrl": "https://cdn.sofifa.net/players/216/433/22_120.png"
    },
    {
      "id": "210635",
      "name": "Kortney Hause",
      "position": "CB",
      "positionGroup": "DEF",
      "rating": 75,
      "nationality": "England",
      "photoUrl": "https://cdn.sofifa.net/players/210/635/22_120.png"
    },
    {
      "id": "222994",
      "name": "Marvelous Nakamba",
      "position": "CDM",
      "positionGroup": "MID",
      "rating": 75,
      "nationality": "Zimbabwe",
      "photoUrl": "https://cdn.sofifa.net/players/222/994/22_120.png"
    },
    {
      "id": "226078",
      "name": "Mahmoud Ahmed Ibrahim Hassan",
      "position": "RM",
      "positionGroup": "MID",
      "rating": 75,
      "nationality": "Egypt",
      "photoUrl": "https://cdn.sofifa.net/players/226/078/22_120.png"
    },
    {
      "id": "231485",
      "name": "Axel Tuanzebe",
      "position": "CB",
      "positionGroup": "DEF",
      "rating": 74,
      "nationality": "England",
      "photoUrl": "https://cdn.sofifa.net/players/231/485/22_120.png"
    },
    {
      "id": "192317",
      "name": "Jed Steer",
      "position": "GK",
      "positionGroup": "GK",
      "rating": 72,
      "nationality": "England",
      "photoUrl": "https://cdn.sofifa.net/players/192/317/22_120.png"
    },
    {
      "id": "231743",
      "name": "Keinan Davis",
      "position": "ST",
      "positionGroup": "FWD",
      "rating": 69,
      "nationality": "England",
      "photoUrl": "https://cdn.sofifa.net/players/231/743/22_120.png"
    },
    {
      "id": "246923",
      "name": "Jacob Ramsey",
      "position": "CAM",
      "positionGroup": "MID",
      "rating": 68,
      "nationality": "England",
      "photoUrl": "https://cdn.sofifa.net/players/246/923/22_120.png"
    },
    {
      "id": "259356",
      "name": "Carney Chibueze Chukwuemeka",
      "position": "CAM",
      "positionGroup": "MID",
      "rating": 63,
      "nationality": "England",
      "photoUrl": "https://cdn.sofifa.net/players/259/356/22_120.png"
    },
    {
      "id": "261336",
      "name": "Jaden Philogene-Bidace",
      "position": "RW",
      "positionGroup": "FWD",
      "rating": 60,
      "nationality": "England",
      "photoUrl": "https://cdn.sofifa.net/players/261/336/22_120.png"
    },
    {
      "id": "258930",
      "name": "Cameron Archer",
      "position": "ST",
      "positionGroup": "FWD",
      "rating": 58,
      "nationality": "England",
      "photoUrl": "https://cdn.sofifa.net/players/258/930/22_120.png"
    },
    {
      "id": "264209",
      "name": "Lamare Bogarde",
      "position": "CB",
      "positionGroup": "DEF",
      "rating": 58,
      "nationality": "Netherlands",
      "photoUrl": "https://cdn.sofifa.net/players/264/209/22_120.png"
    },
    {
      "id": "258748",
      "name": "Chigozier Caleb Chukwuemeka",
      "position": "ST",
      "positionGroup": "FWD",
      "rating": 57,
      "nationality": "England",
      "photoUrl": "https://cdn.sofifa.net/players/258/748/22_120.png"
    },
    {
      "id": "264410",
      "name": "Hayden Lindley",
      "position": "CDM",
      "positionGroup": "MID",
      "rating": 57,
      "nationality": "England",
      "photoUrl": "https://cdn.sofifa.net/players/264/410/22_120.png"
    },
    {
      "id": "264411",
      "name": "Sil Swinkels",
      "position": "CB",
      "positionGroup": "DEF",
      "rating": 56,
      "nationality": "Netherlands",
      "photoUrl": "https://cdn.sofifa.net/players/264/411/22_120.png"
    },
    {
      "id": "258928",
      "name": "Viljami Sinisalo",
      "position": "GK",
      "positionGroup": "GK",
      "rating": 55,
      "nationality": "Finland",
      "photoUrl": "https://cdn.sofifa.net/players/258/928/22_120.png"
    },
    {
      "id": "256556",
      "name": "Ben Chrisene",
      "position": "LB",
      "positionGroup": "DEF",
      "rating": 53,
      "nationality": "England",
      "photoUrl": "https://cdn.sofifa.net/players/256/556/22_120.png"
    }
  ],
  "stats": {
    "min": 61.45454545454545,
    "max": 78.0,
    "mean": 70.46825454545458,
    "p10": 67.27272727272727,
    "p25": 68.81818181818181,
    "p50": 70.54545454545455,
    "p75": 72.0909090909091,
    "p90": 73.54545454545455,
    "samples": [
      61.45454545454545,
      64.54545454545455,
      65.54545454545455,
      65.9090909090909,
      66.18181818181819,
      66.36363636363636,
      66.63636363636364,
      66.81818181818181,
      67.0,
      67.0909090909091,
      67.27272727272727,
      67.36363636363636,
      67.54545454545455,
      67.63636363636364,
      67.72727272727273,
      67.81818181818181,
      68.0,
      68.0909090909091,
      68.18181818181819,
      68.27272727272727,
      68.36363636363636,
      68.45454545454545,
      68.54545454545455,
      68.63636363636364,
      68.72727272727273,
      68.81818181818181,
      68.9090909090909,
      69.0,
      69.0909090909091,
      69.18181818181819,
      69.18181818181819,
      69.27272727272727,
      69.36363636363636,
      69.45454545454545,
      69.45454545454545,
      69.54545454545455,
      69.63636363636364,
      69.72727272727273,
      69.72727272727273,
      69.81818181818181,
      69.9090909090909,
      70.0,
      70.0,
      70.0909090909091,
      70.18181818181819,
      70.18181818181819,
      70.27272727272727,
      70.36363636363636,
      70.45454545454545,
      70.45454545454545,
      70.54545454545455,
      70.63636363636364,
      70.63636363636364,
      70.72727272727273,
      70.81818181818181,
      70.81818181818181,
      70.9090909090909,
      71.0,
      71.0,
      71.0909090909091,
      71.18181818181819,
      71.18181818181819,
      71.27272727272727,
      71.36363636363636,
      71.36363636363636,
      71.45454545454545,
      71.54545454545455,
      71.54545454545455,
      71.63636363636364,
      71.72727272727273,
      71.81818181818181,
      71.81818181818181,
      71.9090909090909,
      72.0,
      72.0909090909091,
      72.0909090909091,
      72.18181818181819,
      72.27272727272727,
      72.36363636363636,
      72.45454545454545,
      72.54545454545455,
      72.63636363636364,
      72.63636363636364,
      72.81818181818181,
      72.81818181818181,
      73.0,
      73.0909090909091,
      73.18181818181819,
      73.27272727272727,
      73.36363636363636,
      73.54545454545455,
      73.72727272727273,
      73.81818181818181,
      74.0,
      74.18181818181819,
      74.45454545454545,
      74.72727272727273,
      75.0,
      75.36363636363636,
      75.9090909090909
    ]
  }
}