{
  "clubId": "dortmund",
  "era": "2022",
  "label": "2022",
  "players": [
    {
      "id": "239085",
      "name": "Erling Braut Haaland",
      "position": "ST",
      "positionGroup": "FWD",
      "rating": 88,
      "nationality": "Norway",
      "photoUrl": "https://cdn.sofifa.net/players/239/085/22_120.png"
    },
    {
      "id": "178603",
      "name": "Mats Hummels",
      "position": "CB",
      "positionGroup": "DEF",
      "rating": 86,
      "nationality": "Germany",
      "photoUrl": "https://cdn.sofifa.net/players/178/603/22_120.png"
    },
    {
      "id": "188350",
      "name": "Marco Reus",
      "position": "CAM",
      "positionGroup": "MID",
      "rating": 85,
      "nationality": "Germany",
      "photoUrl": "https://cdn.sofifa.net/players/188/350/22_120.png"
    },
    {
      "id": "209889",
      "name": "Raphaël Adelino José Guerreiro",
      "position": "LB",
      "positionGroup": "DEF",
      "rating": 84,
      "nationality": "Portugal",
      "photoUrl": "https://cdn.sofifa.net/players/209/889/22_120.png"
    },
    {
      "id": "177413",
      "name": "Axel Witsel",
      "position": "CDM",
      "positionGroup": "MID",
      "rating": 83,
      "nationality": "Belgium",
      "photoUrl": "https://cdn.sofifa.net/players/177/413/22_120.png"
    },
    {
      "id": "203486",
      "name": "Thorgan Hazard",
      "position": "LM",
      "positionGroup": "MID",
      "rating": 82,
      "nationality": "Belgium",
      "photoUrl": "https://cdn.sofifa.net/players/203/486/22_120.png"
    },
    {
      "id": "208333",
      "name": "Emre Can",
      "position": "CM",
      "positionGroup": "MID",
      "rating": 82,
      "nationality": "Germany",
      "photoUrl": "https://cdn.sofifa.net/players/208/333/22_120.png"
    },
    {
      "id": "212194",
      "name": "Julian Brandt",
      "position": "CAM",
      "positionGroup": "MID",
      "rating": 81,
      "nationality": "Germany",
      "photoUrl": "https://cdn.sofifa.net/players/212/194/22_120.png"
    },
    {
      "id": "189117",
      "name": "Roman Bürki",
      "position": "GK",
      "positionGroup": "GK",
      "rating": 80,
      "nationality": "Switzerland",
      "photoUrl": "https://cdn.sofifa.net/players/189/117/22_120.png"
    },
    {
      "id": "229237",
      "name": "Manuel Obafemi Akanji",
      "position": "CB",
      "positionGroup": "DEF",
      "rating": 80,
      "nationality": "Switzerland",
      "photoUrl": "https://cdn.sofifa.net/players/229/237/22_120.png"
    },
    {
      "id": "231447",
      "name": "Donyell Malen",
      "position": "ST",
      "positionGroup": "FWD",
      "rating": 80,
      "nationality": "Netherlands",
      "photoUrl": "https://cdn.sofifa.net/players/231/447/22_120.png"
    },
    {
      "id": "218339",
      "name": "Mahmoud Dahoud",
      "position": "CM",
      "positionGroup": "MID",
      "rating": 79,
      "nationality": "Germany",
      "photoUrl": "https://cdn.sofifa.net/players/218/339/22_120.png"
    },
    {
      "id": "235073",
      "name": "Gregor Kobel",
      "position": "GK",
      "positionGroup": "GK",
      "rating": 79,
      "nationality": "Switzerland",
      "photoUrl": "https://cdn.sofifa.net/players/235/073/22_120.png"
    },
    {
      "id": "252371",
      "name": "Jude Victor William Bellingham",
      "position": "CM",
      "positionGroup": "MID",
      "rating": 79,
      "nationality": "England",
      "photoUrl": "https://cdn.sofifa.net/players/252/371/22_120.png"
    },
    {
      "id": "190243",
      "name": "Marwin Hitz",
      "position": "GK",
      "positionGroup": "GK",
      "rating": 78,
      "nationality": "Switzerland",
      "photoUrl": "https://cdn.sofifa.net/players/190/243/22_120.png"
    },
    {
      "id": "238476",
      "name": "Dan-Axel Zagadou",
      "position": "CB",
      "positionGroup": "DEF",
      "rating": 78,
      "nationality": "France",
      "photoUrl": "https://cdn.sofifa.net/players/238/476/22_120.png"
    },
    {
      "id": "200536",
      "name": "Nico Schulz",
      "position": "LB",
      "positionGroup": "DEF",
      "rating": 77,
      "nationality": "Germany",
      "photoUrl": "https://cdn.sofifa.net/players/200/536/22_120.png"
    },
    {
      "id": "202371",
      "name": "Thomas Meunier",
      "position": "RB",
      "positionGroup": "DEF",
      "rating": 77,
      "nationality": "Belgium",
      "photoUrl": "https://cdn.sofifa.net/players/202/371/22_120.png"
    },
    {
      "id": "245541",
      "name": "Giovanni Alejandro Reyna",
      "position": "CAM",
      "positionGroup": "MID",
      "rating": 77,
      "nationality": "United States",
      "photoUrl": "https://cdn.sofifa.net/players/245/541/22_120.png"
    },
    {
      "id": "224425",
      "name": "Marius Wolf",
      "position": "RM",
      "positionGroup": "MID",
      "rating": 75,
      "nationality": "Germany",
      "photoUrl": "https://cdn.sofifa.net/players/224/425/22_120.png"
    },
    {
      "id": "238370",
      "name": "Marin Pongračić",
      "position": "CB",
      "positionGroup": "DEF",
      "rating": 75,
      "nationality": "Croatia",
      "photoUrl": "https://cdn.sofifa.net/players/238/370/22_120.png"
    },
    {
      "id": "248820",
      "name": "Mateu Jaume Morey Bauzá",
      "position": "RB",
      "positionGroup": "DEF",
      "rating": 73,
      "nationality": "Spain",
      "photoUrl": "https://cdn.sofifa.net/players/248/820/22_120.png"
    },
    {
      "id": "188802",
      "name": "Marcel Schmelzer",
      "position": "LB",
      "positionGroup": "DEF",
      "rating": 71,
      "nationality": "Germany",
      "photoUrl": "https://cdn.sofifa.net/players/188/802/22_120.png"
    },
    {
      "id": "254544",
      "name": "Reinier Jesus Carvalho",
      "position": "CF",
      "positionGroup": "FWD",
      "rating": 71,
      "nationality": "Brazil",
      "photoUrl": "https://cdn.sofifa.net/players/254/544/22_120.png"
    },
    {
      "id": "228080",
      "name": "Felix Passlack",
      "position": "RM",
      "positionGroup": "MID",
      "rating": 70,
      "nationality": "Germany",
      "photoUrl": "https://cdn.sofifa.net/players/228/080/22_120.png"
    },
    {
      "id": "257540",
      "name": "Ansgar Knauff",
      "position": "RM",
      "positionGroup": "MID",
      "rating": 67,
      "nationality": "Germany",
      "photoUrl": "https://cdn.sofifa.net/players/257/540/22_120.png"
    },
    {
      "id": "238656",
      "name": "Steffen Tigges",
      "position": "ST",
      "positionGroup": "FWD",
      "rating": 66,
      "nationality": "Germany",
      "photoUrl": "https://cdn.sofifa.net/players/238/656/22_120.png"
    },
    {
      "id": "247721",
      "name": "Tobias Raschl",
      "position": "CM",
      "positionGroup": "MID",
      "rating": 65,
      "nationality": "Germany",
      "photoUrl": "https://cdn.sofifa.net/players/247/721/22_120.png"
    },
    {
      "id": "261495",
      "name": "Soumaila Coulibaly",
      "position": "CB",
      "positionGroup": "DEF",
      "rating": 61,
      "nationality": "France",
      "photoUrl": "https://cdn.sofifa.net/players/261/495/22_120.png"
    },
    {
      "id": "256500",
      "name": "Nnamdi Collins",
      "position": "CB",
      "positionGroup": "DEF",
      "rating": 60,
      "nationality": "Germany",
      "photoUrl": "https://cdn.sofifa.net/players/256/500/22_120.png"
    },
    {
      "id": "262988",
      "name": "Göktan Gürpüz",
      "position": "CM",
      "positionGroup": "MID",
      "rating": 57,
      "nationality": "Turkey",
      "photoUrl": "https://cdn.sofifa.net/players/262/988/22_120.png"
    }
  ],
  "stats": {
    "min": 69.0909090909091,
    "max": 80.81818181818181,
    "mean": 75.78443636363654,
    "p10": 73.45454545454545,
    "p25": 74.63636363636364,
    "p50": 75.81818181818181,
    "p75": 77.0909090909091,
    "p90": 78.0909090909091,
    "samples": [
      69.0909090909091,
      71.18181818181819,
      71.9090909090909,
      72.18181818181819,
      72.45454545454545,
      72.63636363636364,
      72.81818181818181,
      73.0,
      73.18181818181819,
      73.27272727272727,
      73.45454545454545,
      73.54545454545455,
      73.63636363636364,
      73.72727272727273,
      73.72727272727273,
      73.81818181818181,
      73.9090909090909,
      74.0,
      74.0909090909091,
      74.18181818181819,
      74.27272727272727,
      74.27272727272727,
      74.36363636363636,
      74.45454545454545,
      74.54545454545455,
      74.63636363636364,
      74.63636363636364,
      74.72727272727273,
      74.81818181818181,
      74.81818181818181,
      74.9090909090909,
      74.9090909090909,
      75.0,
      75.0,
      75.0909090909091,
      75.18181818181819,
      75.18181818181819,
      75.27272727272727,
      75.27272727272727,
      75.36363636363636,
      75.36363636363636,
      75.45454545454545,
      75.45454545454545,
      75.54545454545455,
      75.54545454545455,
      75.63636363636364,
      75.63636363636364,
      75.72727272727273,
      75.72727272727273,
      75.81818181818181,
      75.81818181818181,
      75.9090909090909,
      75.9090909090909,
      76.0,
      76.0,
      76.0909090909091,
      76.0909090909091,
      76.0909090909091,
      76.18181818181819,
      76.27272727272727,
      76.27272727272727,
      76.36363636363636,
      76.36363636363636,
      76.45454545454545,
      76.45454545454545,
      76.54545454545455,
      76.63636363636364,
      76.63636363636364,
      76.72727272727273,
      76.72727272727273,
      76.81818181818181,
      76.9090909090909,
      76.9090909090909,
      77.0,
      77.0,
      77.0909090909091,
      77.18181818181819,
      77.18181818181819,
      77.27272727272727,
      77.27272727272727,
      77.36363636363636,
      77.45454545454545,
      77.45454545454545,
      77.54545454545455,
      77.63636363636364,
      77.72727272727273,
      77.72727272727273,
      77.81818181818181,
      77.9090909090909,
      78.0,
      78.0909090909091,
      78.27272727272727,
      78.36363636363636,
      78.45454545454545,
      78.54545454545455,
      78.63636363636364,
      78.81818181818181,
      79.0,
      79.27272727272727,
      79.63636363636364
    ]
  }
}