{
  "clubId": "man-utd",
  "era": "2015",
  "label": "2015",
  "players": [
    {
      "id": "7826",
      "name": "Robin van Persie",
      "position": "ST",
      "positionGroup": "FWD",
      "rating": 88,
      "nationality": "Netherlands",
      "photoUrl": "https://cdn.sofifa.net/players/007/826/15_120.png"
    },
    {
      "id": "167397",
      "name": "Radamel Falcao García Zárate",
      "position": "ST",
      "positionGroup": "FWD",
      "rating": 88,
      "nationality": "Colombia",
      "photoUrl": "https://cdn.sofifa.net/players/167/397/15_120.png"
    },
    {
      "id": "54050",
      "name": "Wayne Mark Rooney",
      "position": "ST",
      "positionGroup": "FWD",
      "rating": 86,
      "nationality": "England",
      "photoUrl": "https://cdn.sofifa.net/players/054/050/15_120.png"
    },
    {
      "id": "183898",
      "name": "Ángel Fabián Di María Hernández",
      "position": "CAM",
      "positionGroup": "MID",
      "rating": 86,
      "nationality": "Argentina",
      "photoUrl": "https://cdn.sofifa.net/players/183/898/15_120.png"
    },
    {
      "id": "178088",
      "name": "Juan Manuel Mata García",
      "position": "CAM",
      "positionGroup": "MID",
      "rating": 85,
      "nationality": "Spain",
      "photoUrl": "https://cdn.sofifa.net/players/178/088/15_120.png"
    },
    {
      "id": "193080",
      "name": "David De Gea Quintana",
      "position": "GK",
      "positionGroup": "GK",
      "rating": 83,
      "nationality": "Spain",
      "photoUrl": "https://cdn.sofifa.net/players/193/080/15_120.png"
    },
    {
      "id": "167905",
      "name": "Luis Antonio Valencia Mosquera",
      "position": "RM",
      "positionGroup": "MID",
      "rating": 80,
      "nationality": "Ecuador",
      "photoUrl": "https://cdn.sofifa.net/players/167/905/15_120.png"
    },
    {
      "id": "21146",
      "name": "Michael Carrick",
      "position": "CM",
      "positionGroup": "MID",
      "rating": 79,
      "nationality": "England",
      "photoUrl": "https://cdn.sofifa.net/players/021/146/15_120.png"
    },
    {
      "id": "169588",
      "name": "Jonathan Grant Evans",
      "position": "CB",
      "positionGroup": "DEF",
      "rating": 79,
      "nationality": "Northern Ireland",
      "photoUrl": "https://cdn.sofifa.net/players/169/588/15_120.png"
    },
    {
      "id": "176944",
      "name": "Marouane Fellaini-Bakkioui",
      "position": "CDM",
      "positionGroup": "MID",
      "rating": 79,
      "nationality": "Belgium",
      "photoUrl": "https://cdn.sofifa.net/players/176/944/15_120.png"
    },
    {
      "id": "190815",
      "name": "Daley Blind",
      "position": "CDM",
      "positionGroup": "MID",
      "rating": 79,
      "nationality": "Netherlands",
      "photoUrl": "https://cdn.sofifa.net/players/190/815/15_120.png"
    },
    {
      "id": "191740",
      "name": "Ander Herrera Agüera",
      "position": "CM",
      "positionGroup": "MID",
      "rating": 79,
      "nationality": "Spain",
      "photoUrl": "https://cdn.sofifa.net/players/191/740/15_120.png"
    },
    {
      "id": "194957",
      "name": "Phil Jones",
      "position": "CB",
      "positionGroup": "DEF",
      "rating": 79,
      "nationality": "England",
      "photoUrl": "https://cdn.sofifa.net/players/194/957/15_120.png"
    },
    {
      "id": "201862",
      "name": "Faustino Marcos Alberto Rojo",
      "position": "CB",
      "positionGroup": "DEF",
      "rating": 79,
      "nationality": "Argentina",
      "photoUrl": "https://cdn.sofifa.net/players/201/862/15_120.png"
    },
    {
      "id": "152908",
      "name": "Ashley Young",
      "position": "LM",
      "positionGroup": "MID",
      "rating": 78,
      "nationality": "England",
      "photoUrl": "https://cdn.sofifa.net/players/152/908/15_120.png"
    },
    {
      "id": "135043",
      "name": "Anders Rosenkrantz Lindegaard",
      "position": "GK",
      "positionGroup": "GK",
      "rating": 77,
      "nationality": "Denmark",
      "photoUrl": "https://cdn.sofifa.net/players/135/043/15_120.png"
    },
    {
      "id": "189681",
      "name": "Rafael Pereira da Silva",
      "position": "RB",
      "positionGroup": "DEF",
      "rating": 77,
      "nationality": "Brazil",
      "photoUrl": "https://cdn.sofifa.net/players/189/681/15_120.png"
    },
    {
      "id": "189881",
      "name": "Chris Smalling",
      "position": "CB",
      "positionGroup": "DEF",
      "rating": 76,
      "nationality": "England",
      "photoUrl": "https://cdn.sofifa.net/players/189/881/15_120.png"
    },
    {
      "id": "138782",
      "name": "Darren Fletcher",
      "position": "CM",
      "positionGroup": "MID",
      "rating": 75,
      "nationality": "Scotland",
      "photoUrl": "https://cdn.sofifa.net/players/138/782/15_120.png"
    },
    {
      "id": "205988",
      "name": "Luke Shaw",
      "position": "LB",
      "positionGroup": "DEF",
      "rating": 75,
      "nationality": "England",
      "photoUrl": "https://cdn.sofifa.net/players/205/988/15_120.png"
    },
    {
      "id": "208330",
      "name": "Adnan Januzaj",
      "position": "LM",
      "positionGroup": "MID",
      "rating": 75,
      "nationality": "Belgium",
      "photoUrl": "https://cdn.sofifa.net/players/208/330/15_120.png"
    },
    {
      "id": "167963",
      "name": "Anderson Luis de Abreu Oliveira",
      "position": "CM",
      "positionGroup": "MID",
      "rating": 73,
      "nationality": "Brazil",
      "photoUrl": "https://cdn.sofifa.net/players/167/963/15_120.png"
    },
    {
      "id": "207494",
      "name": "Jesse Lingard",
      "position": "CAM",
      "positionGroup": "MID",
      "rating": 68,
      "nationality": "England",
      "photoUrl": "https://cdn.sofifa.net/players/207/494/15_120.png"
    },
    {
      "id": "173531",
      "name": "Benjamin Paul Amos",
      "position": "GK",
      "positionGroup": "GK",
      "rating": 65,
      "nationality": "England",
      "photoUrl": "https://cdn.sofifa.net/players/173/531/15_120.png"
    },
    {
      "id": "206094",
      "name": "Marnick Danny Vermijl",
      "position": "RB",
      "positionGroup": "DEF",
      "rating": 65,
      "nationality": "Belgium",
      "photoUrl": "https://cdn.sofifa.net/players/206/094/15_120.png"
    },
    {
      "id": "203265",
      "name": "Tyler Blackett",
      "position": "CB",
      "positionGroup": "DEF",
      "rating": 64,
      "nationality": "England",
      "photoUrl": "https://cdn.sofifa.net/players/203/265/15_120.png"
    },
    {
      "id": "213642",
      "name": "James Anthony Wilson",
      "position": "ST",
      "positionGroup": "FWD",
      "rating": 63,
      "nationality": "England",
      "photoUrl": "https://cdn.sofifa.net/players/213/642/15_120.png"
    },
    {
      "id": "206075",
      "name": "Sam Johnstone",
      "position": "GK",
      "positionGroup": "GK",
      "rating": 62,
      "nationality": "England",
      "photoUrl": "https://cdn.sofifa.net/players/206/075/15_120.png"
    },
    {
      "id": "201911",
      "name": "William David Keane",
      "position": "ST",
      "positionGroup": "FWD",
      "rating": 60,
      "nationality": "England",
      "photoUrl": "https://cdn.sofifa.net/players/201/911/15_120.png"
    },
    {
      "id": "206091",
      "name": "Tom Thorpe",
      "position": "CB",
      "positionGroup": "DEF",
      "rating": 60,
      "nationality": "England",
      "photoUrl": "https://cdn.sofifa.net/players/206/091/15_120.png"
    },
    {
      "id": "211514",
      "name": "Reece James",
      "position": "LB",
      "positionGroup": "DEF",
      "rating": 56,
      "nationality": "England",
      "photoUrl": "https://cdn.sofifa.net/players/211/514/15_120.png"
    },
    {
      "id": "208450",
      "name": "Andreas Hugo Hoelgebaum Pereira",
      "position": "CAM",
      "positionGroup": "MID",
      "rating": 55,
      "nationality": "Belgium",
      "photoUrl": "https://cdn.sofifa.net/players/208/450/15_120.png"
    },
    {
      "id": "213693",
      "name": "Joe Rothwell",
      "position": "CM",
      "positionGroup": "MID",
      "rating": 49,
      "nationality": "England",
      "photoUrl": "https://cdn.sofifa.net/players/213/693/15_120.png"
    }
  ],
  "stats": {
    "min": 64.54545454545455,
    "max": 82.0909090909091,
    "mean": 73.46667272727201,
    "p10": 70.0909090909091,
    "p25": 71.72727272727273,
    "p50": 73.54545454545455,
    "p75": 75.27272727272727,
    "p90": 76.63636363636364,
    "samples": [
      64.54545454545455,
      67.72727272727273,
      68.27272727272727,
      68.63636363636364,
      69.0,
      69.27272727272727,
      69.45454545454545,
      69.63636363636364,
      69.81818181818181,
      70.0,
      70.0909090909091,
      70.27272727272727,
      70.36363636363636,
      70.54545454545455,
      70.63636363636364,
      70.81818181818181,
      70.9090909090909,
      71.0,
      71.0909090909091,
      71.27272727272727,
      71.27272727272727,
      71.45454545454545,
      71.54545454545455,
      71.63636363636364,
      71.72727272727273,
      71.72727272727273,
      71.9090909090909,
      71.9090909090909,
      72.0,
      72.0909090909091,
      72.18181818181819,
      72.27272727272727,
      72.27272727272727,
      72.36363636363636,
      72.45454545454545,
      72.54545454545455,
      72.54545454545455,
      72.63636363636364,
      72.72727272727273,
      72.81818181818181,
      72.9090909090909,
      72.9090909090909,
      73.0,
      73.0909090909091,
      73.18181818181819,
      73.18181818181819,
      73.27272727272727,
      73.36363636363636,
      73.45454545454545,
      73.45454545454545,
      73.54545454545455,
      73.63636363636364,
      73.63636363636364,
      73.72727272727273,
      73.81818181818181,
      73.81818181818181,
      73.9090909090909,
      74.0,
      74.0,
      74.0909090909091,
      74.18181818181819,
      74.18181818181819,
      74.27272727272727,
      74.36363636363636,
      74.45454545454545,
      74.54545454545455,
      74.54545454545455,
      74.63636363636364,
      74.72727272727273,
      74.81818181818181,
      74.81818181818181,
      74.9090909090909,
      75.0,
      75.0909090909091,
      75.18181818181819,
      75.27272727272727,
      75.36363636363636,
      75.45454545454545,
      75.45454545454545,
      75.54545454545455,
      75.63636363636364,
      75.72727272727273,
      75.81818181818181,
      75.9090909090909,
      76.0,
      76.0909090909091,
      76.18181818181819,
      76.27272727272727,
      76.45454545454545,
      76.54545454545455,
      76.63636363636364,
      76.81818181818181,
      77.0,
      77.0909090909091,
      77.27272727272727,
      77.45454545454545,
      77.72727272727273,
      78.0,
      78.36363636363636,
      79.0
    ]
  }
}