{
  "clubId": "roma",
  "era": "2022",
  "label": "2022",
  "players": [
    {
      "id": "192883",
      "name": "Henrikh Mkhitaryan",
      "position": "CF",
      "positionGroup": "FWD",
      "rating": 83,
      "nationality": "Armenia",
      "photoUrl": "https://cdn.sofifa.net/players/192/883/22_120.png"
    },
    {
      "id": "202884",
      "name": "Leonardo Spinazzola",
      "position": "LWB",
      "positionGroup": "DEF",
      "rating": 83,
      "nationality": "Italy",
      "photoUrl": "https://cdn.sofifa.net/players/202/884/22_120.png"
    },
    {
      "id": "178005",
      "name": "Rui Pedro dos Santos Patrício",
      "position": "GK",
      "positionGroup": "GK",
      "rating": 82,
      "nationality": "Portugal",
      "photoUrl": "https://cdn.sofifa.net/players/178/005/22_120.png"
    },
    {
      "id": "201519",
      "name": "Jordan Veretout",
      "position": "CDM",
      "positionGroup": "MID",
      "rating": 82,
      "nationality": "France",
      "photoUrl": "https://cdn.sofifa.net/players/201/519/22_120.png"
    },
    {
      "id": "228251",
      "name": "Lorenzo Pellegrini",
      "position": "CAM",
      "positionGroup": "MID",
      "rating": 81,
      "nationality": "Italy",
      "photoUrl": "https://cdn.sofifa.net/players/228/251/22_120.png"
    },
    {
      "id": "229582",
      "name": "Gianluca Mancini",
      "position": "CB",
      "positionGroup": "DEF",
      "rating": 80,
      "nationality": "Italy",
      "photoUrl": "https://cdn.sofifa.net/players/229/582/22_120.png"
    },
    {
      "id": "190813",
      "name": "Stephan El Shaarawy",
      "position": "LW",
      "positionGroup": "FWD",
      "rating": 79,
      "nationality": "Italy",
      "photoUrl": "https://cdn.sofifa.net/players/190/813/22_120.png"
    },
    {
      "id": "187936",
      "name": "Steven N'Kemboanza Mike Christopher Nzonzi",
      "position": "CDM",
      "positionGroup": "MID",
      "rating": 78,
      "nationality": "France",
      "photoUrl": "https://cdn.sofifa.net/players/187/936/22_120.png"
    },
    {
      "id": "189881",
      "name": "Chris Smalling",
      "position": "CB",
      "positionGroup": "DEF",
      "rating": 78,
      "nationality": "England",
      "photoUrl": "https://cdn.sofifa.net/players/189/881/22_120.png"
    },
    {
      "id": "208268",
      "name": "Bryan Cristante",
      "position": "CDM",
      "positionGroup": "MID",
      "rating": 78,
      "nationality": "Italy",
      "photoUrl": "https://cdn.sofifa.net/players/208/268/22_120.png"
    },
    {
      "id": "222558",
      "name": "Rick Karsdorp",
      "position": "RM",
      "positionGroup": "MID",
      "rating": 78,
      "nationality": "Netherlands",
      "photoUrl": "https://cdn.sofifa.net/players/222/558/22_120.png"
    },
    {
      "id": "231352",
      "name": "Tammy Bakumo-Abraham",
      "position": "ST",
      "positionGroup": "FWD",
      "rating": 78,
      "nationality": "England",
      "photoUrl": "https://cdn.sofifa.net/players/231/352/22_120.png"
    },
    {
      "id": "238067",
      "name": "Nicolò Zaniolo",
      "position": "CAM",
      "positionGroup": "MID",
      "rating": 78,
      "nationality": "Italy",
      "photoUrl": "https://cdn.sofifa.net/players/238/067/22_120.png"
    },
    {
      "id": "247257",
      "name": "Roger Ibañez Da Silva",
      "position": "CB",
      "positionGroup": "DEF",
      "rating": 77,
      "nationality": "Brazil",
      "photoUrl": "https://cdn.sofifa.net/players/247/257/22_120.png"
    },
    {
      "id": "228635",
      "name": "Borja Mayoral Moya",
      "position": "ST",
      "positionGroup": "FWD",
      "rating": 76,
      "nationality": "Spain",
      "photoUrl": "https://cdn.sofifa.net/players/228/635/22_120.png"
    },
    {
      "id": "230613",
      "name": "Amadou Diawara",
      "position": "CDM",
      "positionGroup": "MID",
      "rating": 76,
      "nationality": "Guinea",
      "photoUrl": "https://cdn.sofifa.net/players/230/613/22_120.png"
    },
    {
      "id": "244393",
      "name": "Gonzalo Villar del Fraile",
      "position": "CM",
      "positionGroup": "MID",
      "rating": 76,
      "nationality": "Spain",
      "photoUrl": "https://cdn.sofifa.net/players/244/393/22_120.png"
    },
    {
      "id": "253290",
      "name": "Matías Viña",
      "position": "LB",
      "positionGroup": "DEF",
      "rating": 76,
      "nationality": "Uruguay",
      "photoUrl": "https://cdn.sofifa.net/players/253/290/22_120.png"
    },
    {
      "id": "179847",
      "name": "Federico Julián Fazio",
      "position": "CB",
      "positionGroup": "DEF",
      "rating": 75,
      "nationality": "Argentina",
      "photoUrl": "https://cdn.sofifa.net/players/179/847/22_120.png"
    },
    {
      "id": "240654",
      "name": "Carles Pérez Sayol",
      "position": "RW",
      "positionGroup": "FWD",
      "rating": 75,
      "nationality": "Spain",
      "photoUrl": "https://cdn.sofifa.net/players/240/654/22_120.png"
    },
    {
      "id": "245426",
      "name": "Marash Kumbulla",
      "position": "CB",
      "positionGroup": "DEF",
      "rating": 75,
      "nationality": "Albania",
      "photoUrl": "https://cdn.sofifa.net/players/245/426/22_120.png"
    },
    {
      "id": "189484",
      "name": "Davide Santon",
      "position": "RWB",
      "positionGroup": "DEF",
      "rating": 74,
      "nationality": "Italy",
      "photoUrl": "https://cdn.sofifa.net/players/189/484/22_120.png"
    },
    {
      "id": "239964",
      "name": "Eldor Shomurodov",
      "position": "ST",
      "positionGroup": "FWD",
      "rating": 71,
      "nationality": "Uzbekistan",
      "photoUrl": "https://cdn.sofifa.net/players/239/964/22_120.png"
    },
    {
      "id": "244363",
      "name": "Daniel Cerântula Fuzato",
      "position": "GK",
      "positionGroup": "GK",
      "rating": 68,
      "nationality": "Brazil",
      "photoUrl": "https://cdn.sofifa.net/players/244/363/22_120.png"
    },
    {
      "id": "257711",
      "name": "Riccardo Calafiori",
      "position": "LB",
      "positionGroup": "DEF",
      "rating": 68,
      "nationality": "Italy",
      "photoUrl": "https://cdn.sofifa.net/players/257/711/22_120.png"
    },
    {
      "id": "242907",
      "name": "Bryan Reynolds",
      "position": "RWB",
      "positionGroup": "DEF",
      "rating": 66,
      "nationality": "United States",
      "photoUrl": "https://cdn.sofifa.net/players/242/907/22_120.png"
    },
    {
      "id": "262091",
      "name": "Ebrima Darboe",
      "position": "CDM",
      "positionGroup": "MID",
      "rating": 66,
      "nationality": "Gambia",
      "photoUrl": "https://cdn.sofifa.net/players/262/091/22_120.png"
    },
    {
      "id": "262113",
      "name": "Nicola Zalewski",
      "position": "CAM",
      "positionGroup": "MID",
      "rating": 63,
      "nationality": "Poland",
      "photoUrl": "https://cdn.sofifa.net/players/262/113/22_120.png"
    },
    {
      "id": "246861",
      "name": "Alessio Riccardi",
      "position": "CM",
      "positionGroup": "MID",
      "rating": 62,
      "nationality": "Italy",
      "photoUrl": "https://cdn.sofifa.net/players/246/861/22_120.png"
    },
    {
      "id": "262171",
      "name": "Edoardo Bove",
      "position": "CM",
      "positionGroup": "MID",
      "rating": 61,
      "nationality": "Italy",
      "photoUrl": "https://cdn.sofifa.net/players/262/171/22_120.png"
    },
    {
      "id": "259721",
      "name": "Filippo Tripi",
      "position": "CB",
      "positionGroup": "DEF",
      "rating": 60,
      "nationality": "Italy",
      "photoUrl": "https://cdn.sofifa.net/players/259/721/22_120.png"
    },
    {
      "id": "259973",
      "name": "Pietro Boer",
      "position": "GK",
      "positionGroup": "GK",
      "rating": 54,
      "nationality": "Italy",
      "photoUrl": "https://cdn.sofifa.net/players/259/973/22_120.png"
    }
  ],
  "stats": {
    "min": 68.0,
    "max": 79.54545454545455,
    "mean": 74.03192727272678,
    "p10": 71.63636363636364,
    "p25": 72.81818181818181,
    "p50": 74.0909090909091,
    "p75": 75.27272727272727,
    "p90": 76.36363636363636,
    "samples": [
      68.0,
      69.9090909090909,
      70.45454545454545,
      70.63636363636364,
      70.9090909090909,
      71.0909090909091,
      71.18181818181819,
      71.27272727272727,
      71.45454545454545,
      71.54545454545455,
      71.63636363636364,
      71.72727272727273,
      71.81818181818181,
      71.9090909090909,
      72.0,
      72.0909090909091,
      72.18181818181819,
      72.27272727272727,
      72.36363636363636,
      72.45454545454545,
      72.45454545454545,
      72.54545454545455,
      72.63636363636364,
      72.63636363636364,
      72.72727272727273,
      72.81818181818181,
      72.9090909090909,
      72.9090909090909,
      73.0,
      73.0,
      73.0909090909091,
      73.0909090909091,
      73.18181818181819,
      73.27272727272727,
      73.27272727272727,
      73.36363636363636,
      73.36363636363636,
      73.45454545454545,
      73.45454545454545,
      73.54545454545455,
      73.63636363636364,
      73.63636363636364,
      73.63636363636364,
      73.72727272727273,
      73.81818181818181,
      73.81818181818181,
      73.9090909090909,
      73.9090909090909,
      74.0,
      74.0,
      74.0909090909091,
      74.0909090909091,
      74.18181818181819,
      74.18181818181819,
      74.27272727272727,
      74.27272727272727,
      74.36363636363636,
      74.36363636363636,
      74.45454545454545,
      74.45454545454545,
      74.54545454545455,
      74.54545454545455,
      74.63636363636364,
      74.63636363636364,
      74.72727272727273,
      74.81818181818181,
      74.81818181818181,
      74.9090909090909,
      74.9090909090909,
      75.0,
      75.0,
      75.0909090909091,
      75.18181818181819,
      75.18181818181819,
      75.27272727272727,
      75.27272727272727,
      75.36363636363636,
      75.45454545454545,
      75.45454545454545,
      75.54545454545455,
      75.54545454545455,
      75.63636363636364,
      75.72727272727273,
      75.72727272727273,
      75.81818181818181,
      75.9090909090909,
      76.0,
      76.0909090909091,
      76.0909090909091,
      76.18181818181819,
      76.36363636363636,
      76.45454545454545,
      76.54545454545455,
      76.72727272727273,
      76.81818181818181,
      76.9090909090909,
      77.18181818181819,
      77.36363636363636,
      77.54545454545455,
      78.0
    ]
  }
}